raccoon/__init__.py
raccoon/dataframe.py
raccoon/series.py
raccoon/sort_utils.py
raccoon/utils.py
raccoon-3.3.1.dist-info/licenses/LICENSE
raccoon-3.3.1.dist-info/METADATA
raccoon-3.3.1.dist-info/WHEEL
raccoon-3.3.1.dist-info/top_level.txt
raccoon-3.3.1.dist-info/RECORD
