Metadata-Version: 2.4
Name: raccoon
Version: 3.3.1
Summary: Python DataFrame with fast insert and appends
Author-email: Ryan Sheftel <rsheftel@alumni.upenn.edu>
License: MIT
Project-URL: Homepage, https://github.com/rsheftel/raccoon
Project-URL: Source, https://github.com/rsheftel/raccoon
Project-URL: Documentation, https://raccoon.readthedocs.io/en/latest/
Keywords: dataframe,data,structure
Classifier: Development Status :: 5 - Production/Stable
Classifier: Intended Audience :: Developers
Classifier: Topic :: Software Development
Classifier: License :: OSI Approved :: MIT License
Classifier: Programming Language :: Python :: 3.11
Classifier: Programming Language :: Python :: 3.12
Classifier: Programming Language :: Python :: 3.13
Classifier: Programming Language :: Python :: 3.14
Requires-Python: >=3.11
License-File: LICENSE
Requires-Dist: tabulate
Dynamic: license-file
